aw_watcher_ask_away/__about__.py
aw_watcher_ask_away/__init__.py
aw_watcher_ask_away/__main__.py
aw_watcher_ask_away/_debug_utils.py
aw_watcher_ask_away/core.py
aw_watcher_ask_away/dialog.py
aw_watcher_ask_away-0.0.6.dist-info/METADATA
aw_watcher_ask_away-0.0.6.dist-info/WHEEL
aw_watcher_ask_away-0.0.6.dist-info/entry_points.txt
aw_watcher_ask_away-0.0.6.dist-info/licenses/LICENSE
aw_watcher_ask_away-0.0.6.dist-info/RECORD
