Metadata-Version: 2.1
Name: aw-watcher-ask-away
Version: 0.0.6
Summary: Ask what you were doing when coming back to your computer after a break and log it in Activity Watch.
Project-URL: Documentation, https://github.com/Jeremiah-England/aw-watcher-ask-away#readme
Project-URL: Issues, https://github.com/Jeremiah-England/aw-watcher-ask-away/issues
Project-URL: Source, https://github.com/Jeremiah-England/aw-watcher-ask-away
Author-email: Jeremiah England <englandtuning@gmail.com>
License-Expression: MIT
License-File: LICENSE
Classifier: Development Status :: 4 - Beta
Classifier: Programming Language :: Python
Classifier: Programming Language :: Python :: 3.11
Classifier: Programming Language :: Python :: Implementation :: CPython
Requires-Python: >=3.11
Requires-Dist: appdirs
Requires-Dist: aw-client
